syn_client/__init__.py
syn_client/core/__init__.py
syn_client/core/kafka_client_len.py
syn_client/core/redis_client_len.py
syn_client/core/utils.py
syn_client-1.0.6.dist-info/DESCRIPTION.rst
syn_client-1.0.6.dist-info/METADATA
syn_client-1.0.6.dist-info/RECORD
syn_client-1.0.6.dist-info/WHEEL
syn_client-1.0.6.dist-info/metadata.json
syn_client-1.0.6.dist-info/top_level.txt
